Unknown6656/__init__.py
Unknown6656/CVGL/__init__.py
Unknown6656/CVGL/pixel_shader.py
Unknown6656/CVGL/shader_generator.py
Unknown6656/CVGL/shader_variable.py
Unknown6656/CVGL/Shaders/__init__.py
Unknown6656/CVGL/Shaders/blur.py
Unknown6656/CVGL/Shaders/color_effects.py
Unknown6656/CVGL/Shaders/convolution.py
Unknown6656/CVGL/Shaders/pixelation.py
Unknown6656/CVGL/Shaders/vignette.py
Unknown6656.CVGLPixelShader-2.0.0.dist-info/LICENSE.md
Unknown6656.CVGLPixelShader-2.0.0.dist-info/METADATA
Unknown6656.CVGLPixelShader-2.0.0.dist-info/WHEEL
Unknown6656.CVGLPixelShader-2.0.0.dist-info/top_level.txt
Unknown6656.CVGLPixelShader-2.0.0.dist-info/RECORD
