Metadata-Version: 2.1
Name: Unknown6656.CVGLPixelShader
Version: 2.0.0
Summary: A small package wich enables the modification of OpenCV or NumPy images using OpenGL pixel shaders written in GLSL.
Author-email: Unknown6656 <invalid@unknown6656.com>
Project-URL: Homepage, https://github.com/Unknown6656-Megacorp/Unknown6656.CVGLPixelShader
Project-URL: Bug Tracker, https://github.com/Unknown6656-Megacorp/Unknown6656.CVGLPixelShader/issues
Classifier: Programming Language :: Python :: 3.10
Classifier: License :: OSI Approved :: MIT License
Classifier: Operating System :: OS Independent
Classifier: Environment :: GPU :: NVIDIA CUDA :: 5.0
Classifier: License :: OSI Approved :: GNU Affero General Public License v3 or later (AGPLv3+)
Classifier: Topic :: Multimedia :: Graphics
Requires-Python: >=3.10
License-File: LICENSE.md
Requires-Dist: glfw (>=2.5.5)
Requires-Dist: numpy (>=1.22.2)
Requires-Dist: opencv-python (>=4.5.5.62)
Requires-Dist: PyOpenGL (>=3.1.6)
Requires-Dist: setuptools (>=58.1.0)
